nqtgbot/__init__.py
nqtgbot/message.py
nqtgbot/provider.py
nqtgbot/quotas.py
nqtgbot/resources/config_schema.json
nqtgbot-1.0.0a7.dist-info/LICENSE
nqtgbot-1.0.0a7.dist-info/METADATA
nqtgbot-1.0.0a7.dist-info/WHEEL
nqtgbot-1.0.0a7.dist-info/RECORD
